pylib/__init__.py
pylib/commons.py
py_mannerism-0.0.1.dist-info/LICENSE
py_mannerism-0.0.1.dist-info/METADATA
py_mannerism-0.0.1.dist-info/WHEEL
py_mannerism-0.0.1.dist-info/top_level.txt
py_mannerism-0.0.1.dist-info/RECORD
