Metadata-Version: 2.1
Name: py-mannerism
Version: 0.0.1
Summary: Test library example for pypi.
Home-page: https://github.com/namikazebadri/PythonLibrary
Author: Unis Badri
Author-email: unis.badri@elementcreativestudio.com
License: UNKNOWN
Platform: UNKNOWN
Classifier: Programming Language :: Python :: 3
Classifier: License :: OSI Approved :: MIT License
Classifier: Operating System :: OS Independent
Requires-Python: >=3.6
